github4api/__init__.py
github4api/core/__init__.py
github4api/exceptions/__init__.py
github4api/handlers/__init__.py
github4api/handlers/request_handler/__init__.py
github4api/handlers/user_handler/__init__.py
github4api/scraper/__init__.py
tests/__init__.py
github4api-1.1.15.dist-info/LICENSE
github4api-1.1.15.dist-info/METADATA
github4api-1.1.15.dist-info/WHEEL
github4api-1.1.15.dist-info/top_level.txt
github4api-1.1.15.dist-info/RECORD
