Metadata-Version: 2.1
Name: github4api
Version: 1.1.15
Summary: A python Package API for getting Github Users Information.
Author: Shervin Badanara (shervinbdndev)
Author-email: shervin2234@gmail.com
Maintainer: Shervin Badanara
License: MIT
Project-URL: Source, https://www.github.com/shervinbdndev/github4api/
Keywords: python,api,github,github_api,github_package
Classifier: Development Status :: 5 - Production/Stable
Classifier: Intended Audience :: Developers
Classifier: Programming Language :: Python :: 3
Classifier: Operating System :: Unix
Classifier: Operating System :: MacOS :: MacOS X
Classifier: Operating System :: Microsoft :: Windows
License-File: LICENSE
Requires-Dist: bs4
Requires-Dist: colorama
Requires-Dist: html5lib
Requires-Dist: requests
Requires-Dist: poetry
Requires-Dist: setuptools
Requires-Dist: wheel
Provides-Extra: dev
Requires-Dist: check-manifest ; extra == 'dev'
Provides-Extra: test
Requires-Dist: coverage ; extra == 'test'
